cdreek_algorithms/__init__.py
cdreek_algorithms/bubble.py
cdreek_algorithms/insertion.py
cdreek_algorithms/quick.py
cdreek_algorithms/selection.py
cd_alg-0.3.dist-info/METADATA
cd_alg-0.3.dist-info/WHEEL
cd_alg-0.3.dist-info/top_level.txt
cd_alg-0.3.dist-info/RECORD
