Metadata-Version: 2.1
Name: cd-alg
Version: 0.3
Summary: algorithms package exercise
Home-page: UNKNOWN
Author: cdreek
Author-email: cdreek@example.com
License: MIT
Platform: UNKNOWN
